labscript_c_extensions/__init__.py
labscript_c_extensions/__version__.py
labscript_c_extensions/runviewer/__init__.py
labscript_c_extensions/runviewer/resample.cp312-win32.pyd
labscript_c_extensions-1.2.1.dist-info/licenses/LICENSE.txt
labscript_c_extensions-1.2.1.dist-info/METADATA
labscript_c_extensions-1.2.1.dist-info/WHEEL
labscript_c_extensions-1.2.1.dist-info/top_level.txt
labscript_c_extensions-1.2.1.dist-info/RECORD
