Metadata-Version: 2.4
Name: labscript-c-extensions
Version: 1.2.1
Summary: A module containing C-extensions for the labscript suite
Author-email: The labscript suite community <labscriptsuite@googlegroups.com>
License: BSD 2-Clause License
Project-URL: Homepage, http://labscriptsuite.org/
Project-URL: Documentation, https://docs.labscriptsuite.org/
Project-URL: Repository, https://github.com/labscript-suite/labscript-c-extension/
Project-URL: Downloads, https://github.com/labscript-suite/labscript-c-extension/releases/
Project-URL: Tracker, https://github.com/labscript-suite/labscript-c-extension/issues/
Keywords: experiment control,automation,visualization
Classifier: License :: OSI Approved :: BSD License
Classifier: Programming Language :: Python :: 3 :: Only
Requires-Python: >=3.8
License-File: LICENSE.txt
Requires-Dist: numpy>=1.17.3
Dynamic: license-file
